<?xml version="1.0" encoding="UTF-8" standalone="yes"?>
<TrustFrameworkPolicy
  xmlns:xsi="http://www.w3.org/2001/XMLSchema-instance"
  xmlns:xsd="http://www.w3.org/2001/XMLSchema"
  xmlns="http://schemas.microsoft.com/online/cpim/schemas/2013/06"
  PolicySchemaVersion="0.3.0.0"
  TenantId="nielskilab.onmicrosoft.com"
  PolicyId="B2C_1A_SUSI"
  PublicPolicyUri="http://nielskilab.onmicrosoft.com/B2C_1A_SUSI">

  <BasePolicy>
    <TenantId>nielskilab.onmicrosoft.com</TenantId>
    <PolicyId>B2C_1A_TrustFrameworkExtensions</PolicyId>
  </BasePolicy>

  <BuildingBlocks>    
  </BuildingBlocks>

  <RelyingParty>
      <DefaultUserJourney ReferenceId="SignUpOrSignIn" />
      <TechnicalProfile Id="PolicyProfile">
        <DisplayName>PolicyProfile</DisplayName>
        <Protocol Name="OpenIdConnect" />
        <OutputClaims>
          <OutputClaim ClaimTypeReferenceId="displayName" />
          <OutputClaim ClaimTypeReferenceId="givenName" />
          <!--Sample: Additional claims are not required and were used for testing purposes only -->        
          <!--Sample action Required: Remove after testing--><OutputClaim ClaimTypeReferenceId="extension_AgreedToTermsOfService" />
          <!--Sample action Required: Remove after testing--><OutputClaim ClaimTypeReferenceId="policyTOSversion" />
          <!--Sample action Required: Remove after testing--><OutputClaim ClaimTypeReferenceId="renewalTOSrequired" />
          <OutputClaim ClaimTypeReferenceId="surname" />
          <OutputClaim ClaimTypeReferenceId="email" />
          <OutputClaim ClaimTypeReferenceId="objectId" PartnerClaimType="sub"/>
          <OutputClaim ClaimTypeReferenceId="identityProvider" />
          <OutputClaim ClaimTypeReferenceId="tenantId" AlwaysUseDefaultValue="true" DefaultValue="{Policy:TenantObjectId}" />

          <!-- Added for service consent demo -->
          <OutputClaim ClaimTypeReferenceId="extension_currentConsent" PartnerClaimType="scope" />

        </OutputClaims>
        <SubjectNamingInfo ClaimType="sub" />
      </TechnicalProfile>
    </RelyingParty>

</TrustFrameworkPolicy>